LICENSE
README.md
pyhtransport/__init__.py
pyhtransport/pyhtransport.abi3.so
tsuno-0.1.3.dist-info/METADATA
tsuno-0.1.3.dist-info/WHEEL
tsuno-0.1.3.dist-info/entry_points.txt
tsuno-0.1.3.dist-info/licenses/LICENSE
tsuno/__init__.py
tsuno/__main__.py
tsuno/access_log.py
tsuno/asgi_adapter.py
tsuno/asgi_event_loop_worker.py
tsuno/cli/__init__.py
tsuno/cli/config.py
tsuno/cli/main.py
tsuno/cli/runner.py
tsuno/cli/utils.py
tsuno/constants.py
tsuno/dispatcher.py
tsuno/error_log.py
tsuno/hooks.py
tsuno/log_config.py
tsuno/reload.py
tsuno/unified_server.py
tsuno/wsgi_adapter.py
tsuno-0.1.3.dist-info/RECORD
