Metadata-Version: 2.4
Name: tsuno
Version: 0.1.3
Classifier: Development Status :: 3 - Alpha
Classifier: Intended Audience :: Developers
Classifier: License :: OSI Approved :: MIT License
Classifier: Programming Language :: Python :: 3
Classifier: Programming Language :: Python :: 3.11
Classifier: Programming Language :: Python :: 3.12
Classifier: Programming Language :: Python :: 3.13
Classifier: Programming Language :: Python :: 3.14
Classifier: Programming Language :: Rust
Classifier: Topic :: Software Development :: Libraries :: Python Modules
Classifier: Topic :: Internet :: WWW/HTTP
Requires-Dist: watchfiles>=0.24.0
Requires-Dist: python-dotenv>=1.0.0
Requires-Dist: click>=8.0.0
Requires-Dist: uvloop>=0.22.1
Provides-Extra: server
License-File: LICENSE
Summary: High-performance WSGI/ASGI server for Python, powered by Rust
Keywords: wsgi,asgi,server,rust,async,http2,fastapi,flask,django,starlette,tsuno
Author-email: i2y <>
License-Expression: MIT
Requires-Python: >=3.11
Project-URL: Homepage, https://github.com/i2y/tsuno
Project-URL: Repository, https://github.com/i2y/tsuno
Project-URL: Issues, https://github.com/i2y/tsuno/issues
